pypp_glfw/__init__.py
pypp_glfw/pypp_data/transpiler_config/always_pass_by_value.json
pypp_glfw/pypp_data/transpiler_config/attr_map.json
pypp_glfw/pypp_data/transpiler_config/call_map.json
pypp_glfw/pypp_data/transpiler_config/cmake_lists.json
pypp_glfw/pypp_data/transpiler_config/name_map.json
pypp_glfw/pypp_data/transpiler_config/mapping_functions/glfw_attr.py
pypp_glfw/pypp_data/transpiler_config/mapping_functions/glfw_call.py
pypp_glfw-1.0.0a0.dist-info/METADATA
pypp_glfw-1.0.0a0.dist-info/WHEEL
pypp_glfw-1.0.0a0.dist-info/licenses/LICENSE
pypp_glfw-1.0.0a0.dist-info/RECORD
