Metadata-Version: 2.4
Name: pypp-glfw
Version: 1.0.0a0
Summary: a Py++ library for GLFW
Project-URL: Homepage, https://github.com/curtispuetz/pypp-glfw
Author-email: Curtis Puetz <pypp.main@gmail.com>
License: MIT
License-File: LICENSE
Requires-Python: >=3.13
Requires-Dist: glfw==2.9.0
